retro/agent.py
retro/change_dict.py
retro/errors.py
retro/examples/beast/.gitignore
retro/examples/beast/__init__.py
retro/examples/beast/agents/beast.py
retro/examples/beast/agents/block.py
retro/examples/beast/agents/player.py
retro/examples/beast/board.py
retro/examples/beast/helpers.py
retro/examples/debug.py
retro/examples/nav.py
retro/examples/simple.py
retro/examples/snake.py
retro/examples/virus/__main__.py
retro/examples/virus/token.py
retro/game.py
retro/graph.py
retro/grid.py
retro/validation.py
retro/view.py
retro_games-1.1.0.dist-info/METADATA
retro_games-1.1.0.dist-info/WHEEL
retro_games-1.1.0.dist-info/RECORD
