Metadata-Version: 2.1
Name: retro-games
Version: 1.1.0
Summary: A simple framework for Terminal-based games
Home-page: https://makingwithcode.org
Author: Chris Proctor
Author-email: chris@chrisproctor.net
Requires-Python: >=3.10,<4.0
Classifier: Programming Language :: Python :: 3
Classifier: Programming Language :: Python :: 3.10
Classifier: Programming Language :: Python :: 3.11
Requires-Dist: blessed (>=1.20.0,<2.0.0)
Project-URL: Documentation, https://retro-games.readthedocs.io/en/latest/
